ccas.py
ccas-0.0.6.dist-info/METADATA
ccas-0.0.6.dist-info/WHEEL
ccas-0.0.6.dist-info/top_level.txt
ccas-0.0.6.dist-info/RECORD
